asaquery/__init__.py
asaquery/query.py
asaquery/response.py
asaquery-1.0.1.dist-info/LICENSE
asaquery-1.0.1.dist-info/METADATA
asaquery-1.0.1.dist-info/WHEEL
asaquery-1.0.1.dist-info/top_level.txt
asaquery-1.0.1.dist-info/RECORD
