Metadata-Version: 2.1
Name: asaquery
Version: 1.0.1
Summary: A simple library for querying ASA
Home-page: https://github.com/nattyan-tv/asa-query-py
Author: nattyan-tv
Classifier: Programming Language :: Python :: 3.10
Classifier: License :: OSI Approved :: MIT License
Classifier: Operating System :: OS Independent
License-File: LICENSE
Requires-Dist: requests~=2.32.0
Requires-Dist: aiohttp~=3.11.0
